dagging/__init__.py
dagging/_dagging.py
dagging/_version.py
dagging/tests/__init__.py
dagging/tests/conftest.py
dagging/tests/test_dagging.py
dagging-0.2.2.dist-info/DESCRIPTION.rst
dagging-0.2.2.dist-info/METADATA
dagging-0.2.2.dist-info/RECORD
dagging-0.2.2.dist-info/WHEEL
dagging-0.2.2.dist-info/entry_points.txt
dagging-0.2.2.dist-info/metadata.json
dagging-0.2.2.dist-info/top_level.txt
