Metadata-Version: 2.0
Name: dagging
Version: 0.2.2
Summary: Python package implementing the dagging method
Home-page: https://github.com/chkoar/dagging
Author: Christos Aridas
Author-email: ichkoar@gmail.com
License: BSD (3-clause)
Platform: UNKNOWN
Classifier: Intended Audience :: Science/Research
Classifier: Programming Language :: Python
Classifier: Topic :: Software Development
Classifier: Topic :: Scientific/Engineering
Classifier: Operating System :: Microsoft :: Windows
Classifier: Operating System :: POSIX
Classifier: Operating System :: Unix
Classifier: Operating System :: MacOS
Requires-Dist: numpy
Requires-Dist: scipy
Requires-Dist: scikit-learn
